airflow_gpg_plugin/__init__.py
airflow_gpg_plugin/plugin.py
airflow_gpg_plugin/hooks/__init__.py
airflow_gpg_plugin/hooks/gpg_hook.py
airflow_gpg_plugin/operators/__init__.py
airflow_gpg_plugin/operators/gpg_decrypt_file_operator.py
airflow_gpg_plugin/operators/gpg_encrypt_file_operator.py
tests/hooks/__init__.py
tests/hooks/test_gpg_hook.py
tests/operators/__init__.py
tests/operators/test_gpg_decrypt_file.py
tests/operators/test_gpg_encrypt_file.py
airflow_gpg_plugin-0.2.0.dist-info/LICENSE
airflow_gpg_plugin-0.2.0.dist-info/METADATA
airflow_gpg_plugin-0.2.0.dist-info/WHEEL
airflow_gpg_plugin-0.2.0.dist-info/entry_points.txt
airflow_gpg_plugin-0.2.0.dist-info/top_level.txt
airflow_gpg_plugin-0.2.0.dist-info/RECORD
