Metadata-Version: 2.1
Name: airflow-gpg-plugin
Version: 0.2.0
Summary: Airflow plugin to work with GPG files.
Home-page: https://github.com/tilakpatidar/fibber-csv
Author: Tilak Patidar
Author-email: tilakpatidar@gmail.com
Maintainer: Tilak Patidar
Maintainer-email: tilakpatidar@gmail.com
License: MIT
Platform: UNKNOWN
Classifier: Development Status :: 4 - Beta
Classifier: Intended Audience :: Developers
Classifier: Topic :: Security :: Cryptography
Classifier: Programming Language :: Python
Classifier: Programming Language :: Python :: 3.6
Classifier: Programming Language :: Python :: 3.7
Classifier: Programming Language :: Python :: 3.8
Classifier: Programming Language :: Python :: 3.9
Classifier: Programming Language :: Python :: 3.10
Classifier: Operating System :: OS Independent
Classifier: License :: OSI Approved :: MIT License
Requires-Python: >=3.6.7
License-File: LICENSE
Requires-Dist: apache-airflow (>=2.0.0)
Requires-Dist: python-gnupg (<=0.4.8)
